LICENSE
MANIFEST.in
README.md
conftest.py
setup.cfg
setup.py
wdb.server.py
requirements/development.txt
requirements/production.txt
tests/__init__.py
tests/test_app.py
wdb.server.aiohttp.egg-info/PKG-INFO
wdb.server.aiohttp.egg-info/SOURCES.txt
wdb.server.aiohttp.egg-info/dependency_links.txt
wdb.server.aiohttp.egg-info/not-zip-safe
wdb.server.aiohttp.egg-info/requires.txt
wdb.server.aiohttp.egg-info/top_level.txt
wdb_server/__init__.py
wdb_server/__main__.py
wdb_server/app.py
wdb_server/constants.py
wdb_server/routes.py
wdb_server/views.py
wdb_server/static/images/favicon.ico
wdb_server/static/javascripts/dist/0d8bb5b3ee5f5dac9e446d48480d28a9.woff2
wdb_server/static/javascripts/dist/16b1558858fe1064b5af8cc6c1c4dbf3.woff
wdb_server/static/javascripts/dist/176f8f5bd5f02b3abfcf894955d7e919.woff2
wdb_server/static/javascripts/dist/18d00f739ff1e1c52db1a1c0d9e98129.woff
wdb_server/static/javascripts/dist/1b3b4f49d5b3b3fb2c209e7e68b95e55.jpg
wdb_server/static/javascripts/dist/1ce08cfde36c0d81af5b60c1a4ab895e.woff
wdb_server/static/javascripts/dist/213eedde97d22010287cf492a821e563.woff
wdb_server/static/javascripts/dist/2267169ee7270a22a963b2b2bfb7ab0c.woff
wdb_server/static/javascripts/dist/24a9d3bbf9b715214bf5e83e33574b56.woff
wdb_server/static/javascripts/dist/2900d24e7347deaf65cd76c5294d5bc4.woff
wdb_server/static/javascripts/dist/2ed4651232a34d737777674fb9b2dbf7.woff
wdb_server/static/javascripts/dist/37a7069dc30fc663c8781220e5669d25.woff2
wdb_server/static/javascripts/dist/451d4e559d6f57cdf6a1c54a3e32e11d.woff
wdb_server/static/javascripts/dist/4674f8ded773cb03e824323bfc950537.eot
wdb_server/static/javascripts/dist/498042b7fe9cd07b4fd11a0965093e55.woff
wdb_server/static/javascripts/dist/49ae34d4cc6b98c00c69ab4c41de3e0c.woff
wdb_server/static/javascripts/dist/51aa168dd4ba03bd83f0a799c11a705d.woff2
wdb_server/static/javascripts/dist/535bc89d4af715503b01afd761501e58.woff2
wdb_server/static/javascripts/dist/53b43867955fbecc811a82030cefe8a4.woff2
wdb_server/static/javascripts/dist/5e7382c63da0098d634a356ff441614e.ttf
wdb_server/static/javascripts/dist/640f8692dc49a19f15412c3d3cf7ff2f.woff
wdb_server/static/javascripts/dist/79f21d796f266ce0ea70e74a7fc7b11b.woff
