Metadata-Version: 2.1
Name: wdb.server.aiohttp
Version: 1.1.0.dev1
Summary: An improbable web debugger through WebSockets (server)
Home-page: https://github.com/shepilov-vladislav/wdb_server_aiohttp
Author: Shepilov Vladislav
Author-email: shepilov.v@protonmail.com
License: GPLv3
Platform: Any
Classifier: Development Status :: 4 - Beta
Classifier: Intended Audience :: Developers
Classifier: License :: OSI Approved :: GNU Lesser General Public License v3 or later (LGPLv3+)
Classifier: Operating System :: OS Independent
Classifier: Programming Language :: Python :: 3
Classifier: Programming Language :: Python :: Implementation :: CPython
Classifier: Topic :: Software Development :: Debuggers
